ximalaya-1.3.2.dist-info/METADATA
ximalaya-1.3.2.dist-info/WHEEL
ximalaya-1.3.2.dist-info/entry_points.txt
ximalaya-1.3.2.dist-info/licenses/LICENSE
ximalaya/__init__.py
ximalaya/api/__init__.py
ximalaya/api/category.py
ximalaya/api/mobile.py
ximalaya/api/user.py
ximalaya/core/__init__.py
ximalaya/core/client.py
ximalaya/core/models.py
ximalaya-1.3.2.dist-info/RECORD
